polars_backtest/__init__.py
polars_backtest/_polars_backtest.cpython-313-x86_64-linux-gnu.so
polars_backtest/namespace.py
polars_backtest/namespace.pyi
polars_backtest/polars_backtest.pyi
polars_backtest/py.typed
polars_backtest/utils.py
polars_backtest/wide.py
polars_backtest-0.1.6.dist-info/METADATA
polars_backtest-0.1.6.dist-info/WHEEL
polars_backtest-0.1.6.dist-info/RECORD
