Metadata-Version: 2.4
Name: polars_backtest
Version: 0.1.6
Classifier: Development Status :: 3 - Alpha
Classifier: Intended Audience :: Financial and Insurance Industry
Classifier: Intended Audience :: Science/Research
Classifier: License :: Other/Proprietary License
Classifier: Programming Language :: Python :: 3
Classifier: Programming Language :: Python :: 3.9
Classifier: Programming Language :: Python :: 3.10
Classifier: Programming Language :: Python :: 3.11
Classifier: Programming Language :: Python :: 3.12
Classifier: Programming Language :: Python :: 3.13
Classifier: Programming Language :: Python :: 3.14
Classifier: Programming Language :: Rust
Classifier: Topic :: Office/Business :: Financial :: Investment
Requires-Dist: polars>=1.0.0
Requires-Dist: pyarrow>=21.0.0
Requires-Dist: pytest>=8.0 ; extra == 'dev'
Requires-Dist: pytest-cov ; extra == 'dev'
Requires-Dist: hypothesis ; extra == 'dev'
Provides-Extra: dev
Summary: Polars extension for portfolio backtesting
Keywords: polars,backtest,trading,finance,quantitative
License: PolyForm Noncommercial 1.0.0
Requires-Python: >=3.9
